Displacement_strain_planet/B1986_nmax.py
Displacement_strain_planet/Displacement_strain.py
Displacement_strain_planet/__init__.py
Displacement_strain_planet/_version.py
Displacement_strain_planet-0.5.0.dist-info/LICENSE.txt
Displacement_strain_planet-0.5.0.dist-info/METADATA
Displacement_strain_planet-0.5.0.dist-info/WHEEL
Displacement_strain_planet-0.5.0.dist-info/top_level.txt
Displacement_strain_planet-0.5.0.dist-info/RECORD
