Metadata-Version: 2.1
Name: Displacement-strain-planet
Version: 0.5.0
Summary: Planetary crustal thickness, displacement, stress and strain calculations in spherical harmonics.
Home-page: https://github.com/AB-Ares/Displacement_strain_planet
Author: Adrien Broquet
Author-email: adrienbroquet@arizona.edu
License: UNKNOWN
Keywords: stress,strain,flexure,elastic thickness,crust,gravity,geophysics,Mars,planetary sciences
Platform: UNKNOWN
Classifier: Development Status :: 3 - Alpha
Classifier: Environment :: Console
Classifier: License :: OSI Approved :: GNU General Public License v3 (GPLv3)
Classifier: Intended Audience :: Science/Research
Classifier: Intended Audience :: Developers
Classifier: Natural Language :: English
Classifier: Operating System :: OS Independent
Classifier: Programming Language :: Python
Classifier: Programming Language :: Python :: 3
Classifier: Topic :: Scientific/Engineering :: Physics
Classifier: Topic :: Scientific/Engineering
Requires-Python: >=3.7
Requires-Dist: numpy
Requires-Dist: matplotlib >=3.3
Requires-Dist: sympy
Requires-Dist: jupyter
Requires-Dist: pyshtools >=4.9
Requires-Dist: cmcrameri
